{
  "_class": "group",
  "booleanOperation": -1,
  "clippingMaskMode": 0,
  "do_objectID": "9EE88E7A-216A-498D-92AA-92FF0614E9C8",
  "exportOptions": {
    "_class": "exportOptions",
    "do_objectID": "4158DE49-477B-4861-9159-571028C86F9E",
    "exportFormats": [
    ],
    "includedLayerIds": [
    ],
    "layerOptions": 0,
    "shouldTrim": false
  },
  "frame": {
    "_class": "rect",
    "constrainProportions": false,
    "do_objectID": "1BD23F9F-C917-4DAF-8A05-8A231BFA3ECA",
    "height": 13,
    "width": 1,
    "x": 101.8216216216216,
    "y": 146.2282398452612
  },
  "groupLayout": {
    "_class": "MSImmutableFreeformGroupLayout",
    "do_objectID": "3C81DF19-EE12-4D32-ACD6-FFED4DECE0AC"
  },
  "hasClickThrough": false,
  "hasClippingMask": false,
  "isFixedToViewport": false,
  "isFlippedHorizontal": false,
  "isFlippedVertical": false,
  "isLocked": false,
  "isVisible": true,
  "layerListExpandedType": 0,
  "layers": [
    {
      "class": "shapePath",
      "id": "7FDC4649-C76B-458B-A916-223871BE52A9"
    },
    {
      "class": "shapePath",
      "id": "D78AAA91-8DF9-40BD-9D2E-0F81E258F0BA"
    }
  ],
  "name": "Group 394",
  "nameIsFixed": false,
  "resizingConstraint": 63,
  "resizingType": 0,
  "rotation": 0,
  "shouldBreakMaskChain": false,
  "style": {
    "_class": "style",
    "do_objectID": "73E25699-781A-4BB0-BBB5-5DAE461864B1",
    "endMarkerType": 0,
    "miterLimit": 10,
    "startMarkerType": 0,
    "windingRule": 1
  }
}