{
  "_class": "symbolMaster",
  "allowsOverrides": true,
  "backgroundColor": {
    "_class": "color",
    "alpha": 1,
    "blue": 1,
    "do_objectID": "171D78FC-C8D3-4153-A830-585BD90A1BB0",
    "green": 1,
    "red": 1
  },
  "booleanOperation": 0,
  "changeIdentifier": 386,
  "clippingMaskMode": 0,
  "do_objectID": "378FB05F-2E57-4446-8333-68DBC066C96D",
  "exportOptions": {
    "_class": "exportOptions",
    "do_objectID": "69986F33-5D3B-4020-8C1F-F56D2AB0E626",
    "exportFormats": [
    ],
    "includedLayerIds": [
    ],
    "layerOptions": 0,
    "shouldTrim": false
  },
  "frame": {
    "_class": "rect",
    "constrainProportions": false,
    "do_objectID": "65C556DF-6463-4EF4-B75C-A8C457CC2D14",
    "height": 64,
    "width": 64,
    "x": 208,
    "y": 27950
  },
  "groupLayout": {
    "_class": "MSImmutableFreeformGroupLayout"
  },
  "hasBackgroundColor": false,
  "hasClickThrough": true,
  "hasClippingMask": false,
  "horizontalRulerData": {
    "_class": "rulerData",
    "base": 0,
    "do_objectID": "DDA42BE7-A771-47DC-99A9-DD072E0E100C",
    "guides": [
    ]
  },
  "includeBackgroundColorInExport": true,
  "includeBackgroundColorInInstance": false,
  "includeInCloudUpload": true,
  "isFixedToViewport": false,
  "isFlippedHorizontal": false,
  "isFlippedVertical": false,
  "isFlowHome": false,
  "isLocked": false,
  "isVisible": true,
  "layerListExpandedType": 1,
  "layers": [
    {
      "class": "oval",
      "id": "71738C4D-ABD8-41FC-BD9E-022D74596B8C"
    },
    {
      "class": "group",
      "id": "5C42EF84-ABE0-464D-88E4-DD09ADFE8071"
    }
  ],
  "name": "light/buttons/circle/roster/counter/64/press",
  "nameIsFixed": true,
  "originalObjectID": "35302CD7-4EE1-4F83-984F-FBA6180A95DB",
  "overrideProperties": [
    {
      "_class": "MSImmutableOverrideProperty",
      "canOverride": true,
      "overrideName": "898B03BF-45AF-491B-96A4-6CDC4AC8252F_symbolID"
    },
    {
      "_class": "MSImmutableOverrideProperty",
      "canOverride": false,
      "overrideName": "898B03BF-45AF-491B-96A4-6CDC4AC8252F/62898A45-7410-450F-979E-9FA9968C5CE2_layerStyle"
    },
    {
      "_class": "MSImmutableOverrideProperty",
      "canOverride": false,
      "overrideName": "71738C4D-ABD8-41FC-BD9E-022D74596B8C_layerStyle"
    },
    {
      "_class": "MSImmutableOverrideProperty",
      "canOverride": true,
      "overrideName": "C5F8623B-6B1A-45EE-8EA7-27E0B1AA1668_stringValue"
    }
  ],
  "resizesContent": true,
  "resizingConstraint": 63,
  "resizingType": 0,
  "rotation": 0,
  "shouldBreakMaskChain": true,
  "style": {
    "_class": "style",
    "do_objectID": "343B3A35-D7B8-4F82-97EA-B476B0AC73CE",
    "endMarkerType": 0,
    "miterLimit": 10,
    "startMarkerType": 0,
    "windingRule": 1
  },
  "symbolID": "EBF8498C-BEDC-492B-B734-33B4453D81AA",
  "userInfo": {
    "com.animaapp.stc-sketch-plugin": {
      "kModelPropertiesKey": {
      }
    },
    "com.invisionlabs.library": {
      "version": 33
    }
  },
  "verticalRulerData": {
    "_class": "rulerData",
    "base": 0,
    "do_objectID": "CFE0033B-BD8C-4D81-AAB3-D4B8D8D0A5E4",
    "guides": [
      39,
      26
    ]
  }
}