{
  "_class": "group",
  "booleanOperation": 0,
  "clippingMaskMode": 0,
  "do_objectID": "DE4FB77E-CFE9-41D3-A336-62DDE0191538",
  "exportOptions": {
    "_class": "exportOptions",
    "do_objectID": "B51C459B-2911-4AAD-894B-05FA5DAA6A62",
    "exportFormats": [
    ],
    "includedLayerIds": [
    ],
    "layerOptions": 0,
    "shouldTrim": false
  },
  "frame": {
    "_class": "rect",
    "constrainProportions": false,
    "do_objectID": "E02FBC02-3338-435A-ADBA-E0EFBE880ABB",
    "height": 14,
    "width": 224,
    "x": 12,
    "y": 9
  },
  "groupLayout": {
    "_class": "MSImmutableFreeformGroupLayout"
  },
  "hasClickThrough": false,
  "hasClippingMask": false,
  "isFixedToViewport": false,
  "isFlippedHorizontal": false,
  "isFlippedVertical": false,
  "isLocked": false,
  "isVisible": true,
  "layerListExpandedType": 0,
  "layers": [
    {
      "class": "text",
      "id": "56EB3D10-D4EF-4D72-BB95-EBFBF768DB14"
    },
    {
      "class": "text",
      "id": "5C91860E-2F64-4CB4-8694-965B728D7F32"
    },
    {
      "class": "text",
      "id": "3DE8A850-1ACB-4A7A-B208-5F9F32797668"
    },
    {
      "class": "text",
      "id": "746A6F57-ABA0-4E84-BD82-4E4417713EC8"
    },
    {
      "class": "text",
      "id": "0C311251-7612-449B-BF1E-835B0BF44743"
    },
    {
      "class": "text",
      "id": "5A5017B7-295A-4441-9AB8-09A183C84C49"
    },
    {
      "class": "text",
      "id": "F969F1FF-6255-4B73-9CD7-7AA4C5359C37"
    }
  ],
  "name": "Days",
  "nameIsFixed": false,
  "originalObjectID": "343AE9B4-9820-4E07-BA84-25AC80E8D714",
  "resizingConstraint": 63,
  "resizingType": 0,
  "rotation": 0,
  "shouldBreakMaskChain": false,
  "style": {
    "_class": "style",
    "do_objectID": "03E65841-1B03-4AD9-AB5A-D5119FC8B8AD",
    "endMarkerType": 0,
    "miterLimit": 10,
    "startMarkerType": 0,
    "windingRule": 1
  }
}