{
  "_class": "symbolInstance",
  "booleanOperation": 0,
  "clippingMaskMode": 0,
  "do_objectID": "22C318E0-3F2A-40CE-A776-1BBAD6EDB1BD",
  "exportOptions": {
    "_class": "exportOptions",
    "do_objectID": "AEEF0AB6-1E05-489D-ACBB-9991F1779FE0",
    "exportFormats": [
    ],
    "includedLayerIds": [
    ],
    "layerOptions": 0,
    "shouldTrim": false
  },
  "frame": {
    "_class": "rect",
    "constrainProportions": false,
    "do_objectID": "A5232203-0ABC-4EB7-9378-C57C777F91D7",
    "height": 24,
    "width": 24,
    "x": 26,
    "y": 14
  },
  "hasClippingMask": false,
  "horizontalSpacing": 0,
  "isFixedToViewport": false,
  "isFlippedHorizontal": false,
  "isFlippedVertical": false,
  "isLocked": false,
  "isVisible": true,
  "layerListExpandedType": 0,
  "name": "icon 24",
  "nameIsFixed": true,
  "originalObjectID": "E60E21C1-EEB7-4369-87C1-3FE07A654EBC",
  "overrideValues": [
  ],
  "resizingConstraint": 41,
  "resizingType": 0,
  "rotation": 0,
  "scale": 1,
  "shouldBreakMaskChain": false,
  "style": {
    "_class": "style",
    "do_objectID": "ABD427E6-E0B4-43C7-AE92-05DF10667072",
    "endMarkerType": 0,
    "miterLimit": 10,
    "startMarkerType": 0,
    "windingRule": 1
  },
  "symbolID": "3A22C36A-B810-41A9-9FB5-E523681A085C",
  "userInfo": {
    "com.animaapp.stc-sketch-plugin": {
      "kModelPropertiesKey": {
      }
    }
  },
  "verticalSpacing": 0
}