{
  "_class": "symbolMaster",
  "allowsOverrides": true,
  "backgroundColor": {
    "_class": "color",
    "alpha": 1,
    "blue": 0.1333333333333333,
    "green": 0.1333333333333333,
    "red": 0.1333333333333333
  },
  "booleanOperation": 0,
  "changeIdentifier": 605,
  "clippingMaskMode": 0,
  "do_objectID": "E4BDE940-D8A2-4475-9368-8793C2F533E3",
  "exportOptions": {
    "_class": "exportOptions",
    "exportFormats": [
    ],
    "includedLayerIds": [
    ],
    "layerOptions": 0,
    "shouldTrim": false
  },
  "frame": {
    "_class": "rect",
    "constrainProportions": false,
    "height": 52,
    "width": 139,
    "x": 0,
    "y": 8904
  },
  "groupLayout": {
    "_class": "MSImmutableFreeformGroupLayout"
  },
  "hasBackgroundColor": true,
  "hasClickThrough": true,
  "hasClippingMask": false,
  "horizontalRulerData": {
    "_class": "rulerData",
    "base": 0,
    "guides": [
    ]
  },
  "includeBackgroundColorInExport": true,
  "includeBackgroundColorInInstance": false,
  "includeInCloudUpload": true,
  "isFixedToViewport": false,
  "isFlippedHorizontal": false,
  "isFlippedVertical": false,
  "isFlowHome": false,
  "isLocked": false,
  "isVisible": true,
  "layerListExpandedType": 1,
  "layers": [
    {
      "class": "rectangle",
      "id": "0DE5E503-E112-4E6D-B27C-81725F7F0696"
    },
    {
      "class": "group",
      "id": "67E1F6DB-528F-435A-B0B5-6D17E950F6C3"
    }
  ],
  "name": "dark/buttons/pill/with-icon/52/disable ",
  "nameIsFixed": true,
  "originalObjectID": "E4BDE940-D8A2-4475-9368-8793C2F533E3",
  "overrideProperties": [
    {
      "_class": "MSImmutableOverrideProperty",
      "canOverride": false,
      "overrideName": "0DE5E503-E112-4E6D-B27C-81725F7F0696_layerStyle"
    },
    {
      "_class": "MSImmutableOverrideProperty",
      "canOverride": false,
      "overrideName": "1EEA7D0A-5ACA-4049-9E78-FBB8A5F487B1/6AA718D0-59E5-4697-893D-551E076D2666_layerStyle"
    },
    {
      "_class": "MSImmutableOverrideProperty",
      "canOverride": true,
      "overrideName": "2FFC5BB5-655C-493A-899B-FC8DEA49D36C_stringValue"
    },
    {
      "_class": "MSImmutableOverrideProperty",
      "canOverride": true,
      "overrideName": "1EEA7D0A-5ACA-4049-9E78-FBB8A5F487B1_symbolID"
    }
  ],
  "resizesContent": false,
  "resizingConstraint": 63,
  "resizingType": 0,
  "rotation": 0,
  "shouldBreakMaskChain": true,
  "style": {
    "_class": "style",
    "endMarkerType": 0,
    "fills": [
      {
        "_class": "fill",
        "color": {
          "_class": "color",
          "alpha": 1,
          "blue": 1,
          "green": 1,
          "red": 1
        },
        "fillType": 0,
        "isEnabled": true,
        "noiseIndex": 0,
        "noiseIntensity": 0,
        "patternFillType": 1,
        "patternTileScale": 1
      }
    ],
    "miterLimit": 10,
    "startMarkerType": 0,
    "windingRule": 1
  },
  "symbolID": "F6DAC80F-C25B-4EFC-95FC-529560083E63",
  "userInfo": {
    "com.animaapp.stc-sketch-plugin": {
      "kModelPropertiesKey": {
      }
    },
    "com.invisionlabs.library": {
      "version": 33
    }
  },
  "verticalRulerData": {
    "_class": "rulerData",
    "base": 0,
    "guides": [
    ]
  }
}