{
  "_class": "artboard",
  "backgroundColor": {
    "_class": "color",
    "alpha": 1,
    "blue": 0.17,
    "green": 0.15572,
    "red": 0.1394
  },
  "booleanOperation": 0,
  "clippingMaskMode": 0,
  "do_objectID": "34921FBD-7DB5-4DF0-B354-17CA0FFB31B5",
  "exportOptions": {
    "_class": "exportOptions",
    "do_objectID": "872C00D1-49F3-4325-9203-2A98518885A3",
    "exportFormats": [
      {
        "_class": "exportFormat",
        "absoluteSize": 0,
        "fileFormat": "png",
        "name": "",
        "namingScheme": 0,
        "scale": 2,
        "visibleScaleType": 0
      }
    ],
    "includedLayerIds": [
    ],
    "layerOptions": 0,
    "shouldTrim": false
  },
  "frame": {
    "_class": "rect",
    "constrainProportions": false,
    "do_objectID": "B5F57546-C468-4708-891F-69A63B35B1AC",
    "height": 440,
    "width": 320,
    "x": -46,
    "y": 3303
  },
  "groupLayout": {
    "_class": "MSImmutableFreeformGroupLayout"
  },
  "hasBackgroundColor": true,
  "hasClickThrough": true,
  "hasClippingMask": false,
  "horizontalRulerData": {
    "_class": "rulerData",
    "base": 0,
    "do_objectID": "4C343C1C-CC0E-4EE4-8F00-531DB4DA482C",
    "guides": [
    ]
  },
  "includeBackgroundColorInExport": true,
  "includeInCloudUpload": true,
  "isFixedToViewport": false,
  "isFlippedHorizontal": false,
  "isFlippedVertical": false,
  "isFlowHome": false,
  "isLocked": false,
  "isVisible": true,
  "layerListExpandedType": 1,
  "layers": [
    {
      "class": "symbolInstance",
      "id": "9267BB9E-3556-4709-AB92-71110F69C987"
    },
    {
      "class": "symbolInstance",
      "id": "ED1C0AB0-D73C-4E8E-AE3E-C08E81E169CE"
    },
    {
      "class": "symbolInstance",
      "id": "5FB796D3-2743-42BB-9282-59CBEF7BA76B"
    }
  ],
  "name": "Dark - Form-elements 14.1",
  "nameIsFixed": true,
  "presetDictionary": {
    "allowResizedMatching": 0,
    "height": 440,
    "name": "Momentum - small",
    "offersLandscapeVariant": 0,
    "width": 320
  },
  "resizesContent": false,
  "resizingConstraint": 63,
  "resizingType": 0,
  "rotation": 0,
  "shouldBreakMaskChain": true,
  "style": {
    "_class": "style",
    "do_objectID": "F6A37FE8-7EF4-4F5B-8C17-84446D1E9497",
    "endMarkerType": 0,
    "miterLimit": 10,
    "startMarkerType": 0,
    "windingRule": 1
  },
  "userInfo": {
    "com.animaapp.stc-sketch-plugin": {
      "kModelPropertiesKey": {
      }
    }
  },
  "verticalRulerData": {
    "_class": "rulerData",
    "base": 0,
    "do_objectID": "0FC343BA-B5F4-46F1-BD4B-FCC36C327415",
    "guides": [
    ]
  }
}