{
  "_class": "symbolInstance",
  "booleanOperation": 0,
  "clippingMaskMode": 0,
  "do_objectID": "82350B60-96D0-42B9-B8B0-0CA1B5163F87",
  "exportOptions": {
    "_class": "exportOptions",
    "do_objectID": "7615DF3C-5251-4856-91FE-097138C16001",
    "exportFormats": [
    ],
    "includedLayerIds": [
    ],
    "layerOptions": 0,
    "shouldTrim": false
  },
  "frame": {
    "_class": "rect",
    "constrainProportions": false,
    "do_objectID": "2BF6C887-68BF-4E21-AB77-5857B6891CEC",
    "height": 36,
    "width": 238,
    "x": 393,
    "y": 14
  },
  "hasClippingMask": false,
  "horizontalSpacing": 0,
  "isFixedToViewport": false,
  "isFlippedHorizontal": false,
  "isFlippedVertical": false,
  "isLocked": false,
  "isVisible": true,
  "layerListExpandedType": 0,
  "name": "button",
  "nameIsFixed": true,
  "overrideValues": [
    {
      "_class": "overrideValue",
      "do_objectID": "889F665F-C3E8-48C0-A1F2-EE33B335B8AA",
      "overrideName": "DB60B7DD-F777-40DF-AE79-9FCB59DF3939_symbolID",
      "value": "19455532-3FD5-4B50-B7C6-41A79AE8451B"
    },
    {
      "_class": "overrideValue",
      "do_objectID": "7056C1D1-8239-4D8C-9C37-09BAF4BD2893",
      "overrideName": "DC8B3A2F-D6BD-403B-AF65-8FE36A54DA34_stringValue",
      "value": "Development agenda"
    }
  ],
  "resizingConstraint": 45,
  "resizingType": 0,
  "rotation": 0,
  "scale": 1,
  "shouldBreakMaskChain": false,
  "style": {
    "_class": "style",
    "do_objectID": "42CFE672-1822-4DAE-A01E-123C9BA8FF79",
    "endMarkerType": 0,
    "miterLimit": 10,
    "startMarkerType": 0,
    "windingRule": 1
  },
  "symbolID": "18E8C0F4-57D2-425D-BE3C-0F44B4F760BF",
  "verticalSpacing": 0
}