{
  "_class": "symbolInstance",
  "booleanOperation": 0,
  "clippingMaskMode": 0,
  "do_objectID": "5B8DC31A-E14B-4638-9D22-B063F4B7596E",
  "exportOptions": {
    "_class": "exportOptions",
    "do_objectID": "EA398A0D-3C50-4493-BC45-AA3D31C854F8",
    "exportFormats": [
    ],
    "includedLayerIds": [
    ],
    "layerOptions": 0,
    "shouldTrim": false
  },
  "frame": {
    "_class": "rect",
    "constrainProportions": false,
    "do_objectID": "8E2DBC6A-9C73-4DAF-8B6D-BBD96732B565",
    "height": 28,
    "width": 194,
    "x": 237,
    "y": 4
  },
  "hasClippingMask": false,
  "horizontalSpacing": 0,
  "isFixedToViewport": false,
  "isFlippedHorizontal": false,
  "isFlippedVertical": false,
  "isLocked": false,
  "isVisible": true,
  "layerListExpandedType": 0,
  "name": "button",
  "nameIsFixed": true,
  "overrideValues": [
  ],
  "resizingConstraint": 63,
  "resizingType": 0,
  "rotation": 0,
  "scale": 1,
  "shouldBreakMaskChain": false,
  "style": {
    "_class": "style",
    "blur": {
      "_class": "blur",
      "center": "{0.5, 0.5}",
      "do_objectID": "87EBB092-CA09-4B76-AC70-EA5113A4CAAF",
      "isEnabled": false,
      "motionAngle": 0,
      "radius": 7.777777777777778,
      "saturation": 1,
      "type": 0
    },
    "do_objectID": "3F6023DD-651E-489D-8A57-9298EC082819",
    "endMarkerType": 0,
    "miterLimit": 10,
    "startMarkerType": 0,
    "windingRule": 1
  },
  "symbolID": "435490E3-728E-446D-BD6B-DE7110345C65",
  "userInfo": {
    "com.animaapp.stc-sketch-plugin": {
      "kModelPropertiesKey": {
      }
    }
  },
  "verticalSpacing": 0
}