{
  "_class": "rectangle",
  "booleanOperation": -1,
  "clippingMaskMode": 0,
  "do_objectID": "D59D1987-6B59-408A-BEED-C824C182A92E",
  "edited": false,
  "exportOptions": {
    "_class": "exportOptions",
    "do_objectID": "5670121B-2C9F-4C25-8E9F-938C1A87C17E",
    "exportFormats": [
    ],
    "includedLayerIds": [
    ],
    "layerOptions": 0,
    "shouldTrim": false
  },
  "fixedRadius": 0,
  "frame": {
    "_class": "rect",
    "constrainProportions": false,
    "height": 96,
    "width": 320,
    "x": 0,
    "y": 0
  },
  "hasClippingMask": true,
  "hasConvertedToNewRoundCorners": true,
  "isClosed": true,
  "isFixedToViewport": false,
  "isFlippedHorizontal": false,
  "isFlippedVertical": false,
  "isLocked": false,
  "isVisible": true,
  "layerListExpandedType": 0,
  "name": "mask",
  "nameIsFixed": true,
  "pointRadiusBehaviour": 1,
  "points": [
    {
      "_class": "curvePoint",
      "cornerRadius": 0,
      "curveFrom": "{0, 0}",
      "curveMode": 1,
      "curveTo": "{0, 0}",
      "hasCurveFrom": false,
      "hasCurveTo": false,
      "point": "{0, 0}"
    },
    {
      "_class": "curvePoint",
      "cornerRadius": 0,
      "curveFrom": "{1, 0}",
      "curveMode": 1,
      "curveTo": "{1, 0}",
      "hasCurveFrom": false,
      "hasCurveTo": false,
      "point": "{1, 0}"
    },
    {
      "_class": "curvePoint",
      "cornerRadius": 0,
      "curveFrom": "{1, 1}",
      "curveMode": 1,
      "curveTo": "{1, 1}",
      "hasCurveFrom": false,
      "hasCurveTo": false,
      "point": "{1, 1}"
    },
    {
      "_class": "curvePoint",
      "cornerRadius": 0,
      "curveFrom": "{0, 1}",
      "curveMode": 1,
      "curveTo": "{0, 1}",
      "hasCurveFrom": false,
      "hasCurveTo": false,
      "point": "{0, 1}"
    }
  ],
  "resizingConstraint": 63,
  "resizingType": 0,
  "rotation": 0,
  "shouldBreakMaskChain": false,
  "style": {
    "_class": "style",
    "blur": {
      "_class": "blur",
      "center": "{0.5, 0.5}",
      "do_objectID": "ADF03DC6-DB63-4B5F-96A0-DB94324A395D",
      "isEnabled": false,
      "motionAngle": 0,
      "radius": 48,
      "saturation": 1,
      "type": 3
    },
    "do_objectID": "6208F5B9-C6EF-42C0-AF04-BD5C40E0390C",
    "endMarkerType": 0,
    "miterLimit": 10,
    "startMarkerType": 0,
    "windingRule": 1
  }
}