{
  "_class": "shapePath",
  "booleanOperation": -1,
  "clippingMaskMode": 0,
  "do_objectID": "822A93C9-1773-4B1E-B5D5-B6EF326CDACA",
  "edited": true,
  "exportOptions": {
    "_class": "exportOptions",
    "do_objectID": "D2E9A43D-BA9A-4972-975A-FCD85F3850F3",
    "exportFormats": [
    ],
    "includedLayerIds": [
    ],
    "layerOptions": 0,
    "shouldTrim": false
  },
  "frame": {
    "_class": "rect",
    "constrainProportions": false,
    "do_objectID": "871FF8F6-458E-45AC-A63D-7A0924CD5D48",
    "height": 126.7288682170542,
    "width": 57.82826086956541,
    "x": 252.1717826086955,
    "y": 88.67461085271317
  },
  "hasClippingMask": false,
  "isClosed": false,
  "isFixedToViewport": false,
  "isFlippedHorizontal": false,
  "isFlippedVertical": false,
  "isLocked": false,
  "isVisible": true,
  "layerListExpandedType": 0,
  "name": "Stroke 260",
  "nameIsFixed": false,
  "pointRadiusBehaviour": 1,
  "points": [
    {
      "_class": "curvePoint",
      "cornerRadius": 0,
      "curveFrom": "{0, 1}",
      "curveMode": 1,
      "curveTo": "{0, 1}",
      "hasCurveFrom": false,
      "hasCurveTo": false,
      "point": "{0, 1}"
    },
    {
      "_class": "curvePoint",
      "cornerRadius": 0,
      "curveFrom": "{0.95938498552685958, 1}",
      "curveMode": 4,
      "curveTo": "{0.90927408744032179, 1}",
      "hasCurveFrom": true,
      "hasCurveTo": false,
      "point": "{0.90927408744032179, 1}"
    },
    {
      "_class": "curvePoint",
      "cornerRadius": 0,
      "curveFrom": "{1, 0.95866460680507926}",
      "curveMode": 4,
      "curveTo": "{1, 0.98149550061830104}",
      "hasCurveFrom": false,
      "hasCurveTo": true,
      "point": "{1, 0.95866460680507926}"
    },
    {
      "_class": "curvePoint",
      "cornerRadius": 0,
      "curveFrom": "{1, 0.018507924872143637}",
      "curveMode": 4,
      "curveTo": "{1, 0.04133881868536541}",
      "hasCurveFrom": true,
      "hasCurveTo": false,
      "point": "{1, 0.04133881868536541}"
    },
    {
      "_class": "curvePoint",
      "cornerRadius": 0,
      "curveFrom": "{0.90927408744032179, 0}",
      "curveMode": 4,
      "curveTo": "{0.95938498552685958, 0}",
      "hasCurveFrom": false,
      "hasCurveTo": true,
      "point": "{0.90927408744032179, 0}"
    },
    {
      "_class": "curvePoint",
      "cornerRadius": 0,
      "curveFrom": "{0.32366452389007916, 0}",
      "curveMode": 1,
      "curveTo": "{0.32366452389007916, 0}",
      "hasCurveFrom": false,
      "hasCurveTo": false,
      "point": "{0.32366452389007916, 0}"
    }
  ],
  "resizingConstraint": 63,
  "resizingType": 0,
  "rotation": 0,
  "shouldBreakMaskChain": false,
  "style": {
    "_class": "style",
    "borderOptions": {
      "_class": "borderOptions",
      "dashPattern": [
      ],
      "do_objectID": "A4DB7BB1-CCA7-4987-BC75-AC06D869E536",
      "isEnabled": false,
      "lineCapStyle": 1,
      "lineJoinStyle": 1
    },
    "borders": [
      {
        "_class": "border",
        "color": {
          "_class": "color",
          "alpha": 1,
          "blue": 0.349,
          "green": 0.341,
          "red": 0.325
        },
        "fillType": 0,
        "isEnabled": true,
        "position": 0,
        "thickness": 1
      }
    ],
    "do_objectID": "A2BE35C6-30C4-4F88-85C1-1E83F83E807A",
    "endMarkerType": 0,
    "miterLimit": 10,
    "startMarkerType": 0,
    "windingRule": 1
  }
}