{
  "_class": "symbolMaster",
  "allowsOverrides": true,
  "backgroundColor": {
    "_class": "color",
    "alpha": 1,
    "blue": 0.12,
    "green": 0.1056,
    "red": 0.0912
  },
  "booleanOperation": 0,
  "changeIdentifier": 68,
  "clippingMaskMode": 0,
  "do_objectID": "2321CD10-8DB7-4156-BE4A-97186D36B9A4",
  "exportOptions": {
    "_class": "exportOptions",
    "do_objectID": "92E7CE59-319C-417A-9600-B0410FF052E0",
    "exportFormats": [
    ],
    "includedLayerIds": [
    ],
    "layerOptions": 0,
    "shouldTrim": false
  },
  "frame": {
    "_class": "rect",
    "constrainProportions": false,
    "do_objectID": "08ABF075-CA24-4107-8150-1A97EEEBD2A8",
    "height": 52,
    "width": 320,
    "x": 360,
    "y": 52334
  },
  "groupLayout": {
    "_class": "MSImmutableFreeformGroupLayout"
  },
  "hasBackgroundColor": true,
  "hasClickThrough": true,
  "hasClippingMask": false,
  "horizontalRulerData": {
    "_class": "rulerData",
    "base": 0,
    "do_objectID": "7BEF426D-7DE9-4BC3-BC08-225C744BA074",
    "guides": [
    ]
  },
  "includeBackgroundColorInExport": false,
  "includeBackgroundColorInInstance": false,
  "includeInCloudUpload": true,
  "isFixedToViewport": false,
  "isFlippedHorizontal": false,
  "isFlippedVertical": false,
  "isFlowHome": false,
  "isLocked": false,
  "isVisible": true,
  "layerListExpandedType": 1,
  "layers": [
    {
      "class": "rectangle",
      "id": "4266B94F-7EBE-4B7B-8F22-9F92D3E186FF"
    },
    {
      "class": "group",
      "id": "EF1D1B31-244C-4A72-A6F0-0A2FB70E4518"
    }
  ],
  "name": "ui-templates/core/pairing-button/not-paired/normal",
  "nameIsFixed": false,
  "overrideProperties": [
    {
      "_class": "MSImmutableOverrideProperty",
      "canOverride": true,
      "overrideName": "23C4E74F-A81D-4038-94B0-31A9EAEF3EA6_symbolID"
    },
    {
      "_class": "MSImmutableOverrideProperty",
      "canOverride": true,
      "overrideName": "3C95F5B4-BD9D-465D-A41E-44B07E94446E_stringValue"
    }
  ],
  "resizesContent": false,
  "resizingConstraint": 63,
  "resizingType": 0,
  "rotation": 0,
  "shouldBreakMaskChain": true,
  "style": {
    "_class": "style",
    "do_objectID": "4688E215-947F-4E6C-9E62-C4E479336105",
    "endMarkerType": 0,
    "miterLimit": 10,
    "startMarkerType": 0,
    "windingRule": 1
  },
  "symbolID": "5A6CFDB7-7006-4482-8D87-8F253BD448A4",
  "verticalRulerData": {
    "_class": "rulerData",
    "base": 0,
    "do_objectID": "B1E4ABCA-9E72-4057-9D66-14D517E37324",
    "guides": [
    ]
  }
}